[{"id":1,"title":"New Arrival","description":"10% off","button_text":"Shop Now","button_link":"https://mudey.fr/","image":"navcollection/2024/05/20/téléchargement_3.jpeg","updated_at":"2024-05-21 08:16:12.397137","created_at":"2024-05-20 19:52:21.915985"},{"id":2,"title":"Best seller","description":"15% off","button_text":"Shop Now","button_link":"https://mudey.fr/","image":"navcollection/2024/05/20/téléchargement_2.jpeg","updated_at":"2024-05-20 19:53:50.116293","created_at":"2024-05-20 19:53:50.116293"},{"id":3,"title":"for Kids","description":"20% off","button_text":"Shop Now","button_link":"https://mudey.fr/","image":"navcollection/2024/05/20/baby-staring-laptop-computer-isolated-young-child-striped-shir_x2FlVhY.webp","updated_at":"2024-05-20 19:54:44.774974","created_at":"2024-05-20 19:54:44.774974"}]